keras_balanced_batch_generator.py
keras_balanced_batch_generator-0.0.3.dist-info/LICENSE
keras_balanced_batch_generator-0.0.3.dist-info/METADATA
keras_balanced_batch_generator-0.0.3.dist-info/WHEEL
keras_balanced_batch_generator-0.0.3.dist-info/top_level.txt
keras_balanced_batch_generator-0.0.3.dist-info/RECORD
