Metadata-Version: 2.1
Name: keras-balanced-batch-generator
Version: 0.0.3
Summary: A Keras-compatible generator for creating balanced batches
Home-page: https://github.com/soroushj/keras-balanced-batch-generator
Author: Soroush Javadi
Author-email: soroush.javadi@gmail.com
License: MIT
Keywords: keras,generator
Classifier: Development Status :: 4 - Beta
Classifier: Programming Language :: Python :: 3
Classifier: License :: OSI Approved :: MIT License
Classifier: Operating System :: OS Independent
Classifier: Topic :: Software Development :: Libraries
Classifier: Topic :: Software Development :: Libraries :: Python Modules
Classifier: Intended Audience :: Developers
Classifier: Intended Audience :: Education
Classifier: Intended Audience :: Science/Research
Requires-Python: >=3.0
License-File: LICENSE
Requires-Dist: numpy >=1.0.0
